README.txt
setup.py
docs/HISTORY.txt
docs/INSTALL.txt
docs/LICENSE.GPL
docs/LICENSE.txt
qi/__init__.py
qi.Goban.egg-info/PKG-INFO
qi.Goban.egg-info/SOURCES.txt
qi.Goban.egg-info/dependency_links.txt
qi.Goban.egg-info/entry_points.txt
qi.Goban.egg-info/namespace_packages.txt
qi.Goban.egg-info/not-zip-safe
qi.Goban.egg-info/paster_plugins.txt
qi.Goban.egg-info/requires.txt
qi.Goban.egg-info/top_level.txt
qi/Goban/__init__.py
qi/Goban/config.py
qi/Goban/configure.zcml
qi/Goban/interfaces.py
qi/Goban/tests.py
qi/Goban/version.txt
qi/Goban/browser/__init__.py
qi/Goban/browser/addVariation.py
qi/Goban/browser/configure.zcml
qi/Goban/browser/controls.pt
qi/Goban/browser/controls.py
qi/Goban/browser/exportPDF.py
qi/Goban/browser/gamefolder.pt
qi/Goban/browser/gamefolder.py
qi/Goban/browser/goban.pt
qi/Goban/browser/goban.py
qi/Goban/browser/gogame.css
qi/Goban/browser/gogame.pt
qi/Goban/browser/gogame.py
qi/Goban/browser/recent.pt
qi/Goban/browser/recent.py
qi/Goban/browser/images/b.gif
qi/Goban/browser/images/b.png
qi/Goban/browser/images/back.png
qi/Goban/browser/images/bl.gif
qi/Goban/browser/images/bp.gif
qi/Goban/browser/images/br.gif
qi/Goban/browser/images/bs.gif
qi/Goban/browser/images/bs.png
qi/Goban/browser/images/bt.gif
qi/Goban/browser/images/bt.png
qi/Goban/browser/images/empty.gif
qi/Goban/browser/images/ep.gif
qi/Goban/browser/images/ffwd.png
qi/Goban/browser/images/forw.png
qi/Goban/browser/images/goGame.ico
qi/Goban/browser/images/hp.gif
qi/Goban/browser/images/kaya.png
qi/Goban/browser/images/lp.gif
qi/Goban/browser/images/minus.gif
qi/Goban/browser/images/new_game.gif
qi/Goban/browser/images/plus.gif
qi/Goban/browser/images/rp.gif
qi/Goban/browser/images/rwnd.png
qi/Goban/browser/images/tl.gif
qi/Goban/browser/images/tp.gif
qi/Goban/browser/images/tr.gif
qi/Goban/browser/images/w.gif
qi/Goban/browser/images/w.png
qi/Goban/browser/images/ws.gif
qi/Goban/browser/images/ws.png
qi/Goban/browser/images/wt.gif
qi/Goban/browser/images/wt.png
qi/Goban/browser/portlets/__init__.py
qi/Goban/browser/portlets/configure.zcml
qi/Goban/browser/portlets/recent.pt
qi/Goban/browser/portlets/recent.py
qi/Goban/content/__init__.py
qi/Goban/content/configure.zcml
qi/Goban/content/gogame.py
qi/Goban/kss/GobanKSSCommands.py
qi/Goban/kss/IGobanKSSCommands.py
