Metadata-Version: 1.0
Name: qi.Goban
Version: 1.0
Summary: A product for storing, viewing and annotating Go game records in plone.
Home-page: http://svn.plone.org/svn/collective/qi.Goban
Author: G. Gozadinos
Author-email: ggozad@qiweb.net
License: GPL
Keywords: plone go games
Platform: UNKNOWN
Classifier: Framework :: Plone
Classifier: Framework :: Zope2
Classifier: Framework :: Zope3
Classifier: Programming Language :: Python
Classifier: Topic :: Software Development :: Libraries :: Python Modules
